verilog/verilog.v
module dff(input clk, input [3:0] D, output reg [3:0] Q);
    always @(posedge clk) begin
        Q <= D;
    end
endmodule

module dff1b(input clk, input D, output reg Q);
    always @(posedge clk) begin
        Q <= D;
    end
endmodule

module pcg(input p , input c , input g , output out);
    wire k,l;
    and u1(k,p,c);
    nor u2(l,k,g);
    not u3(out,l);
endmodule

module combine (
    input clk,
    input [3:0] a, // 4-bit input vector for a0, a1, a2, a3
    input [3:0] b, // 4-bit input vector for b0, b1, b2, b3
    input c0,      // Single-bit carry-in
    output [3:0] s, // 4-bit sum output vector
    output cout      // Single-bit carry-out
);
    wire [3:0] aa;
    wire [3:0] bb;
    wire [3:0] s0;
    wire cin,cc;

    dff A1 ( .clk(clk) , .D(a)  , .Q(aa));
    dff B1 ( .clk(clk) , .D(b)  , .Q(bb));
    dff1b C( .clk(clk) , .D(c0) , .Q(cin));
    adder2 add( .a(aa) , .b(bb) , .c0(cin) , .s(s0) , .cout(cc) );
    dff S1 ( .clk(clk) , .D(s0)  , .Q(s));
    dff1b C1( .clk(clk) , .D(cc) , .Q(cout));

endmodule

module adder2 (
    input [3:0] a, // 4-bit input vector for a0, a1, a2, a3
    input [3:0] b, // 4-bit input vector for b0, b1, b2, b3
    input c0,      // Single-bit carry-in
    output [3:0] s, // 4-bit sum output vector
    output cout      // Single-bit carry-out
);
    wire [3:0] p; // Propagate signals
    wire [3:0] g; // Generate signals
    wire [3:0] c; // Carry signals
    wire [3:0] h; // Intermediate wires for NAND logic
    wire [3:0] k; // Intermediate wires for AND logic
    wire [3:0] j; // Intermediate wires for OR logic

    assign c[0] = c0; // Initial carry-in

    // Bit 0 Logic
    xor u1(p[0], a[0], b[0]);
    xor u2(s[0], p[0], c[0]);
    nand u11(h[0], p[0], c[0]);
    nand u12(h[1], a[0], b[0]);
    nand u13(c[1], h[0], h[1]);

    // Bit 1 Logic
    xor u3(p[1], a[1], b[1]);
    xor u4(s[1], p[1], c[1]);
    and u21(g[1], a[1], b[1]);
    pcg u22(.out(c[2]), .p(p[1]), .c(c[1]), .g(g[1]));

    // Bit 2 Logic
    xor u5(p[2], a[2], b[2]);
    xor u6(s[2], p[2], c[2]);
    and u31(g[2], a[2], b[2]);
    and u32(k[1], p[1], p[2], c[1]);
    pcg u33(.out(k[2]), .p(p[2]), .c(g[1]), .g(g[2]));
    or  u34(c[3], k[1], k[2]);

    // Bit 3 Logic
    xor u7(p[3], a[3], b[3]);
    xor u8(s[3], p[3], c[3]);
    and u41(g[3], a[3], b[3]);
    pcg u42(.out(j[1]), .p(p[3]), .c(g[2]), .g(g[3]));
    and u43(j[2], p[1], p[2], p[3], c[1]);
    and u44(j[3], p[2], p[3], g[1]);
    or  u45(cout, j[1], j[2], j[3]);

endmodule

module dff_tb;
    reg clk; reg [3:0] d; wire [3:0] q;
    dff uut( .clk(clk), .D(d), .Q(q) );
    initial begin
        $dumpfile("dff2.vcd");
        $dumpvars(0, dff_tb);
        $monitor($time," D = %b, clk = %b, Q = %b", d, clk, q);
        clk = 0;
        d = 4'b0101;
        #10;
        d = 4'b0010;
        #10
        $finish;
    end
    always #3 clk = ~clk;
endmodule

module adder2_tb;
    reg [3:0] a, b;
    wire [3:0] s;
    wire cout;

    adder2 uut(
        .a(a), .b(b), .c0(1'b0), .s(s), .cout(cout)
    );

    initial begin
        $dumpfile("adder.vcd");
        $dumpvars(0, adder2_tb);
        $monitor($time, " a = %b, b = %b, s = %b, cout = %b", a, b, s, cout);

        a = 4'b1111;
        b = 4'b1111;
        #10;

        a = 4'b1001;
        b = 4'b1010;
        #20

        $finish;
    end
endmodule

module combine_tb;
    reg clk;
    reg [3:0] a, b;
    wire [3:0] s;
    wire cout;

    combine uut(
        .clk(clk), .a(a), .b(b), .c0(1'b0), .s(s), .cout(cout)
    );

    initial begin
        $dumpfile("combine.vcd");
        $dumpvars(0, combine_tb);
        $monitor($time, " a = %b, b = %b, s = %b, cout = %b", a, b, s, cout);
        clk = 0;
        a = 4'b0001;
        b = 4'b0010;
        #5;

        a = 4'b1101;
        b = 4'b1010;
        #5

        a = 4'b1011;
        b = 4'b1001;
        #5

        $finish;
    end
    always #2 clk = ~clk;
endmodule

verilog/adder.vcd
$date
	Mon Dec  2 22:39:52 2024
$end
$version
	Icarus Verilog
$end
$timescale
	1s
$end
$scope module adder2_tb $end
$var wire 4 ! s [3:0] $end
$var wire 1 " cout $end
$var reg 4 # a [3:0] $end
$var reg 4 $ b [3:0] $end
$scope module uut $end
$var wire 4 % a [3:0] $end
$var wire 4 & b [3:0] $end
$var wire 1 ' c0 $end
$var wire 1 " cout $end
$var wire 4 ( s [3:0] $end
$var wire 4 ) p [3:0] $end
$var wire 4 * k [3:0] $end
$var wire 4 + j [3:0] $end
$var wire 4 , h [3:0] $end
$var wire 4 - g [3:0] $end
$var wire 4 . c [3:0] $end
$scope module u22 $end
$var wire 1 / c $end
$var wire 1 0 g $end
$var wire 1 1 k $end
$var wire 1 2 l $end
$var wire 1 3 out $end
$var wire 1 4 p $end
$upscope $end
$scope module u33 $end
$var wire 1 5 c $end
$var wire 1 6 g $end
$var wire 1 7 k $end
$var wire 1 8 l $end
$var wire 1 9 out $end
$var wire 1 : p $end
$upscope $end
$scope module u42 $end
$var wire 1 ; c $end
$var wire 1 < g $end
$var wire 1 = k $end
$var wire 1 > l $end
$var wire 1 ? out $end
$var wire 1 @ p $end
$upscope $end
$upscope $end
$upscope $end
$scope module combine_tb $end
$var wire 4 A s [3:0] $end
$var wire 1 B cout $end
$var reg 4 C a [3:0] $end
$var reg 4 D b [3:0] $end
$var reg 1 E clk $end
$scope module uut $end
$var wire 4 F a [3:0] $end
$var wire 4 G b [3:0] $end
$var wire 1 H c0 $end
$var wire 1 E clk $end
$var wire 4 I s0 [3:0] $end
$var wire 4 J s [3:0] $end
$var wire 1 B cout $end
$var wire 1 K cin $end
$var wire 1 L cc $end
$var wire 4 M bb [3:0] $end
$var wire 4 N aa [3:0] $end
$scope module A1 $end
$var wire 4 O D [3:0] $end
$var wire 1 E clk $end
$var reg 4 P Q [3:0] $end
$upscope $end
$scope module B1 $end
$var wire 4 Q D [3:0] $end
$var wire 1 E clk $end
$var reg 4 R Q [3:0] $end
$upscope $end
$scope module C $end
$var wire 1 H D $end
$var wire 1 E clk $end
$var reg 1 K Q $end
$upscope $end
$scope module C1 $end
$var wire 1 E clk $end
$var wire 1 L D $end
$var reg 1 B Q $end
$upscope $end
$scope module S1 $end
$var wire 1 E clk $end
$var wire 4 S D [3:0] $end
$var reg 4 T Q [3:0] $end
$upscope $end
$scope module add $end
$var wire 4 U a [3:0] $end
$var wire 4 V b [3:0] $end
$var wire 1 K c0 $end
$var wire 1 L cout $end
$var wire 4 W s [3:0] $end
$var wire 4 X p [3:0] $end
$var wire 4 Y k [3:0] $end
$var wire 4 Z j [3:0] $end
$var wire 4 [ h [3:0] $end
$var wire 4 \ g [3:0] $end
$var wire 4 ] c [3:0] $end
$scope module u22 $end
$var wire 1 ^ c $end
$var wire 1 _ g $end
$var wire 1 ` k $end
$var wire 1 a l $end
$var wire 1 b out $end
$var wire 1 c p $end
$upscope $end
$scope module u33 $end
$var wire 1 d c $end
$var wire 1 e g $end
$var wire 1 f k $end
$var wire 1 g l $end
$var wire 1 h out $end
$var wire 1 i p $end
$upscope $end
$scope module u42 $end
$var wire 1 j c $end
$var wire 1 k g $end
$var wire 1 l k $end
$var wire 1 m l $end
$var wire 1 n out $end
$var wire 1 o p $end
$upscope $end
$upscope $end
$upscope $end
$upscope $end
$scope module dff_tb $end
$var wire 4 p q [3:0] $end
$var reg 1 q clk $end
$var reg 4 r d [3:0] $end
$scope module uut $end
$var wire 4 s D [3:0] $end
$var wire 1 q clk $end
$var reg 4 t Q [3:0] $end
$upscope $end
$upscope $end
$enddefinitions $end
$comment Show the parameter values. $end
$dumpall
$end
#0
$dumpvars
bx t
b101 s
b101 r
0q
bx p
xo
xn
xm
xl
xk
xj
xi
xh
xg
xf
xe
xd
xc
xb
xa
x`
x_
x^
bx ]
bxz \
bzxx [
bxz Z
bzxxz Y
bx X
bx W
bx V
bx U
bx T
bx S
bx R
b10 Q
bx P
b1 O
bx N
bx M
xL
xK
bx J
bx I
0H
b10 G
b1 F
0E
b10 D
b1 C
xB
bx A
0@
1?
0>
0=
1<
1;
0:
19
08
07
16
15
04
13
02
01
10
1/
b1110 .
b111z -
bz01 ,
b1z +
bz10z *
b0 )
b1110 (
0'
b1111 &
b1111 %
b1111 $
b1111 #
1"
b1110 !
$end
#2
0L
0b
1a
0h
0n
0`
1g
1m
0^
b11 I
b11 S
b11 W
0f
bz00z Y
0l
b0z Z
1c
0d
0_
0i
0j
0e
0o
0k
b11 X
b0z \
bz11 [
b1 N
b1 P
b1 U
b10 M
b10 R
b10 V
b0 ]
0K
1E
#3
b101 p
b101 t
1q
#4
0E
#5
b1010 D
b1010 G
b1010 Q
b1101 C
b1101 F
b1101 O
#6
1L
b1z Z
1n
b111 I
b111 S
b111 W
0m
1i
1k
b111 X
b100z \
0B
b11 A
b11 J
b11 T
b1010 M
b1010 R
b1010 V
b1101 N
b1101 P
b1101 U
1E
0q
#8
0E
#9
1q
#10
1b
0a
1`
1^
b100 I
b100 S
b100 W
b110 ]
0i
b10 X
bz01 [
b1011 N
b1011 P
b1011 U
b1001 M
b1001 R
b1001 V
b111 A
b111 J
b111 T
1B
0/
03
bz00z *
09
b0 .
01
b11 !
b11 (
12
18
14
05
00
0;
06
bz11 ,
b11 )
b100z -
1E
b1001 D
b1001 G
b1001 Q
b1011 C
b1011 F
b1011 O
b10 r
b10 s
b1010 $
b1010 &
b1001 #
b1001 %
#12
0E
0q
#14
b100 A
b100 J
b100 T
1E
#15
b10 p
b10 t
1q
